pige/__init__.py
pige/pige.py
pige-0.0.1.dist-info/METADATA
pige-0.0.1.dist-info/WHEEL
pige-0.0.1.dist-info/top_level.txt
pige-0.0.1.dist-info/RECORD
