Metadata-Version: 2.1
Name: pige
Version: 0.0.1
Summary: PAI for RAG Evaluation
Home-page: 
Author: Winter.YU
Author-email: winter741258@gmail.com
License: Apache 2.0 License
Keywords: embedding,transformer,pytorch,deep learning
Platform: UNKNOWN
Classifier: Intended Audience :: Developers
Classifier: Intended Audience :: Education
Classifier: Intended Audience :: Science/Research
Classifier: License :: OSI Approved :: Apache Software License
Classifier: Operating System :: OS Independent
Classifier: Programming Language :: Python :: 3
Classifier: Programming Language :: Python :: 3.8
Classifier: Programming Language :: Python :: 3.9
Classifier: Programming Language :: Python :: 3.10
Classifier: Programming Language :: Python :: 3.11
Classifier: Topic :: Scientific/Engineering :: Artificial Intelligence
Requires-Python: >=3.8.0
Requires-Dist: pandas
Requires-Dist: datasets
Requires-Dist: ragas
Requires-Dist: langchain-openai
Requires-Dist: langchain-huggingface
